myllm/__init__.py
myllm/config.py
myllm/main.py
myllm/handler/__init__.py
myllm/handler/_client.py
myllm/handler/crawl4ai.py
myllm/handler/g4f.py
myllm/handler/groq.py
myllm/handler/openai.py
myllm-4.19.15.dist-info/licenses/LICENSE
myllm-4.19.15.dist-info/METADATA
myllm-4.19.15.dist-info/WHEEL
myllm-4.19.15.dist-info/top_level.txt
myllm-4.19.15.dist-info/RECORD
