Metadata-Version: 2.4
Name: MyLLM
Version: 4.19.15
Summary: A python package to interact with llm model supported by g4f and langchain.
Author-email: mraniki <8766259+mraniki@users.noreply.github.com>
License-Expression: MIT
Project-URL: Homepage, https://github.com/mraniki/MyLLM
Project-URL: Changelog, https://github.com/mraniki/MyLLM/blob/dev/CHANGELOG.rst
Project-URL: Support, https://github.com/mraniki/MyLLM/discussions
Project-URL: Issues, https://github.com/mraniki/MyLLM/issues
Keywords: chatgpt,llm,ai,llama,ai,g4f,freegpt
Classifier: Programming Language :: Python :: 3
Classifier: Programming Language :: Python :: 3.10
Classifier: Programming Language :: Python :: 3.11
Classifier: Programming Language :: Python :: 3.12
Requires-Python: >=3.10
License-File: LICENSE
Requires-Dist: fastapi>=0.95.2
Requires-Dist: uvicorn>=0.22.0
Requires-Dist: dynaconf>=3.2.0
Requires-Dist: loguru>=0.6.0
Requires-Dist: httpx>=0.24.1
Requires-Dist: g4f==0.5.5.5
Requires-Dist: js2py~=0.74
Requires-Dist: PyExecJS2==1.6.1
Requires-Dist: curl_cffi==0.11.4
Requires-Dist: Brotli==1.1.0
Requires-Dist: openai==1.92.2
Requires-Dist: groq==0.29.0
Requires-Dist: playwright==1.53.0
Provides-Extra: dev
Requires-Dist: python-semantic-release>=8.0.8; extra == "dev"
Requires-Dist: ruff~=0.11; extra == "dev"
Requires-Dist: pre-commit~=4.0; extra == "dev"
Provides-Extra: test
Requires-Dist: pytest~=8.0; extra == "test"
Requires-Dist: pytest-cov~=6.0; extra == "test"
Requires-Dist: pytest-asyncio~=1.0; extra == "test"
Requires-Dist: pytest-mock~=3.11; extra == "test"
Requires-Dist: pytest-loguru~=0.4; extra == "test"
Provides-Extra: docs
Requires-Dist: sphinx==7.4.7; extra == "docs"
Requires-Dist: pydata-sphinx-theme~=0.14; extra == "docs"
Requires-Dist: sphinx-hoverxref~=1.3; extra == "docs"
Requires-Dist: sphinx_copybutton==0.5.2; extra == "docs"
Requires-Dist: myst_parser~=4.0; extra == "docs"
Requires-Dist: sphinx_design~=0.6; extra == "docs"
Requires-Dist: linkify-it-py==2.0.3; extra == "docs"
Dynamic: license-file
